README.md
setup.cfg
setup.py
spb_label/__init__.py
spb_label/image_sdk.py
spb_label/pointcloud_sdk.py
spb_label/sdk.py
spb_label/sdk_config.py
spb_label/session.py
spb_label/spb_logger.py
spb_label/video_sdk.py
spb_label/command/__init__.py
spb_label/command/builder.py
spb_label/command/commands.py
spb_label/core/__init__.py
spb_label/core/manager.py
spb_label/core/model.py
spb_label/core/query.py
spb_label/core/session.py
spb_label/core/models/__init__.py
spb_label/core/models/attrs/__init__.py
spb_label/core/models/attrs/attributes_container.py
spb_label/core/models/types/__init__.py
spb_label/core/models/types/type.py
spb_label/core/models/types/type_base.py
spb_label/datauri/__init__.py
spb_label/datauri/exceptions.py
spb_label/exceptions/__init__.py
spb_label/exports/__init__.py
spb_label/exports/export.py
spb_label/exports/manager.py
spb_label/exports/query.py
spb_label/exports/session.py
spb_label/labels/__init__.py
spb_label/labels/label.py
spb_label/labels/manager.py
spb_label/labels/query.py
spb_label/labels/session.py
spb_label/labels/serializer/__init__.py
spb_label/labels/serializer/label_info_build_params.py
spb_label/models/__init__.py
spb_label/models/data.py
spb_label/models/label.py
spb_label/models/project.py
spb_label/models/video_data.py
spb_label/models/video_label.py
spb_label/orm/__init__.py
spb_label/orm/json_type.py
spb_label/orm/loading.py
spb_label/orm/manager.py
spb_label/orm/model.py
spb_label/orm/query.py
spb_label/orm/type.py
spb_label/orm/type_base.py
spb_label/orm/utils.py
spb_label/projects/__init__.py
spb_label/projects/manager.py
spb_label/projects/project.py
spb_label/projects/query.py
spb_label/projects/session.py
spb_label/tasks/__init__.py
spb_label/tasks/manager.py
spb_label/tasks/query.py
spb_label/tasks/session.py
spb_label/tasks/task.py
spb_label/users/__init__.py
spb_label/users/manager.py
spb_label/users/query.py
spb_label/users/session.py
spb_label/users/user.py
spb_label/utils/__init__.py
superb_ai_label.egg-info/PKG-INFO
superb_ai_label.egg-info/SOURCES.txt
superb_ai_label.egg-info/dependency_links.txt
superb_ai_label.egg-info/not-zip-safe
superb_ai_label.egg-info/requires.txt
superb_ai_label.egg-info/top_level.txt