Metadata-Version: 2.1
Name: superb-ai-label
Version: 0.22.2
Summary: Suite Standard Library
Home-page: https://github.com/Superb-AI-Suite/superb-ai-label-python.git
Author: Superb AI Dev Team
Author-email: support@superb-ai.com
License: MIT
Platform: UNKNOWN
Classifier: Development Status :: 1 - Planning
Classifier: Intended Audience :: Developers
Classifier: Topic :: Software Development :: Libraries
Classifier: License :: OSI Approved :: MIT License
Classifier: Programming Language :: Python :: 3.7
Classifier: Programming Language :: Python :: 3.8
Classifier: Programming Language :: Python :: 3.9
Classifier: Programming Language :: Python :: 3.10
Classifier: Programming Language :: Python :: 3.11
